drf_caching/__init__.py
drf_caching/cache.py
drf_caching/exceptions.py
drf_caching/keys.py
drf_caching/sentinels.py
drf_caching/settings.py
drf_caching/utils.py
drf_caching-1.6.0.dist-info/METADATA
drf_caching-1.6.0.dist-info/WHEEL
drf_caching-1.6.0.dist-info/licenses/LICENSE
drf_caching-1.6.0.dist-info/RECORD
