Metadata-Version: 2.4
Name: drf-caching
Version: 1.6.0
Summary: Handle views caching in Django Rest Framework.
Project-URL: Homepage, https://github.com/stefanofusai/drf-caching
Project-URL: Repository, https://github.com/stefanofusai/drf-caching
Author-email: Stefano Fusai <stefanofusai@gmail.com>
Maintainer-email: Stefano Fusai <stefanofusai@gmail.com>
License-File: LICENSE
Requires-Python: >=3.12
Requires-Dist: beautifulsoup4<5.0.0,>=4.0.1
Requires-Dist: django-redis<6.0.0,>=5.0.0
Requires-Dist: django<6.0.0,>=5.0.0
Requires-Dist: djangorestframework<4.0.0,>=3.0.0
Requires-Dist: lxml<6.0.0,>=5.0.1
Requires-Dist: pydantic<3.0.0,>=2.8.0
